{
  "name": "green_break_d",
  "particleCount": 10,
  "emissionRate": 5,
  "emitDuration": 0.5,
  "lifetime": 1.1,
  "sizeStart": 1,
  "sizeEnd": 5,
  "colorStart": "#f7f7f7",
  "colorEnd": "#f1e9e9",
  "opacityStart": 0.8,
  "opacityEnd": 0,
  "velocity": 0,
  "spread": 0,
  "emissionShape": "point",
  "gravity": 0,
  "rotationSpeed": 0,
  "turbulence": 0.5,
  "blendMode": "additive",
  "atlasPath": "effect/atlas_g.png",
  "uvStartX": 0.5,
  "uvStartY": 0.6666666666666666,
  "uvEndX": 0.6666666666666666,
  "uvEndY": 0.8333333333333333,
  "particleType": "sprite",
  "faceCamera": true,
  "doubleSided": true,
  "velocityDirX": 0,
  "velocityDirY": 0,
  "velocityDirZ": 0,
  "gridCols": 6,
  "gridRows": 6,
  "lastUpdated": 1763671230904,
  "spawnRotation": 0,
  "randomRotation": false,
  "randomRotationSpeed": false
}